{"Added":[{"Id":70007,"Kind":11,"Name":"ad_EventSubResJnlPostLine","Namespace":""},{"Id":70019,"Kind":10,"Name":"Seminar Ledger Entry","Namespace":""},{"Id":80000,"Kind":22,"Name":"ad_SeminarChargeType","Namespace":""},{"Id":70014,"Kind":12,"Name":"PostedSeminarRegList","Namespace":""},{"Id":70002,"Kind":11,"Name":"ad_SeminarJnlCheckLine","Namespace":""},{"Id":70015,"Kind":17,"Name":"ad_ResJournalLineExt","Namespace":""},{"Id":70009,"Kind":22,"Name":"ad_SeminarRegistrationStatus","Namespace":""},{"Id":70003,"Kind":11,"Name":"ad_SeminarJnlPostLine","Namespace":""},{"Id":80002,"Kind":22,"Name":"ad_SeminarCommentLineDocumentType","Namespace":""},{"Id":80003,"Kind":22,"Name":"ad_SeminarJournalChargeType","Namespace":""},{"Id":70004,"Kind":11,"Name":"ad_SeminarPost","Namespace":""},{"Id":70016,"Kind":17,"Name":"ad_ResLedgerEntryExt","Namespace":""},{"Id":80004,"Kind":22,"Name":"ad_SeminarJournalEntryType","Namespace":""},{"Id":70005,"Kind":11,"Name":"ad_SeminarPostYesNo","Namespace":""},{"Id":70017,"Kind":12,"Name":"PostedSeminarRegistration","Namespace":""},{"Id":70017,"Kind":17,"Name":"ad_ResourceExt","Namespace":""},{"Id":70012,"Kind":12,"Name":"ad_SeminarLedgerEntries","Namespace":""},{"Id":80005,"Kind":22,"Name":"ad_SeminarJournalSourceType","Namespace":""},{"Id":70006,"Kind":11,"Name":"ad_EventSubNavigate","Namespace":""},{"Id":70000,"Kind":11,"Name":"ad_SeminarRegShowLedger","Namespace":""},{"Id":70018,"Kind":17,"Name":"ad_SourceCodeSetupExt","Namespace":""}],"Modified":[{"Id":70013,"Kind":10,"Name":"Posted Seminar Reg. Line","Namespace":""},{"Id":70007,"Kind":10,"Name":"Seminar Registration Line","Namespace":""},{"Id":70014,"Kind":10,"Name":"Posted Seminar Charge","Namespace":""},{"Id":70008,"Kind":10,"Name":"Seminar Charge","Namespace":""},{"Id":70002,"Kind":10,"Name":"Seminar Set Up","Namespace":""},{"Id":80008,"Kind":12,"Name":"Seminar Charges Form","Namespace":""},{"Id":70003,"Kind":10,"Name":"Seminar","Namespace":""},{"Id":80009,"Kind":12,"Name":"Seminar Registration Subpage","Namespace":""},{"Id":80003,"Kind":12,"Name":"Seminar Setup","Namespace":""},{"Id":80010,"Kind":12,"Name":"Seminar Registration","Namespace":""},{"Id":70011,"Kind":10,"Name":"Seminar Register","Namespace":""},{"Id":80004,"Kind":12,"Name":"Seminar Card","Namespace":""},{"Id":70005,"Kind":10,"Name":"Seminar Comment Lines","Namespace":""},{"Id":80011,"Kind":12,"Name":"Seminar Registrations","Namespace":""},{"Id":70012,"Kind":10,"Name":"Posted Seminar Reg. Header","Namespace":""},{"Id":80005,"Kind":12,"Name":"Seminar List","Namespace":""},{"Id":70006,"Kind":10,"Name":"Seminar Registration Header","Namespace":""}],"Removed":[{"Id":50032,"Kind":11,"Name":"ad_SeminarJnlPostLine","Namespace":""},{"Id":50003,"Kind":17,"Name":"ad_ResJournalLineExt","Namespace":""},{"Id":50003,"Kind":22,"Name":"ad_SeminarJournalEntryType","Namespace":""},{"Id":50098,"Kind":11,"Name":"ad_EventSubNavigate","Namespace":""},{"Id":50021,"Kind":12,"Name":"ad_SeminarLedgerEntries","Namespace":""},{"Id":50004,"Kind":22,"Name":"ad_SeminarJournalChargeType","Namespace":""},{"Id":50099,"Kind":11,"Name":"ad_EventSubResJnlPostLine","Namespace":""},{"Id":50004,"Kind":11,"Name":"ad_SeminarRegShowLedger","Namespace":""},{"Id":50005,"Kind":22,"Name":"ad_SeminarJournalSourceType","Namespace":""},{"Id":50034,"Kind":12,"Name":"ad_PostedSeminarRegistration","Namespace":""},{"Id":70010,"Kind":10,"Name":"Seminar Journal Line","Namespace":""},{"Id":50000,"Kind":17,"Name":"ad_ResourceExt","Namespace":""},{"Id":50000,"Kind":22,"Name":"ad_SeminarRegistrationStatus","Namespace":""},{"Id":50036,"Kind":12,"Name":"ad_PostedSeminarRegList","Namespace":""},{"Id":50000,"Kind":11,"Name":"ad_SeminarPost","Namespace":""},{"Id":50001,"Kind":17,"Name":"ad_SourceCodeSetupExt","Namespace":""},{"Id":50001,"Kind":22,"Name":"ad_SeminarCommentLineDocumentType","Namespace":""},{"Id":50031,"Kind":11,"Name":"ad_SeminarJnlCheckLine","Namespace":""},{"Id":50001,"Kind":11,"Name":"ad_SeminarPostYesNo","Namespace":""},{"Id":50002,"Kind":17,"Name":"ad_ResLedgerEntryExt","Namespace":""},{"Id":50002,"Kind":22,"Name":"ad_SeminarChargeType","Namespace":""}]}